setup.cfg
setup.py
bkp879b/__init__.py
bkp879b/scpi.py
bkp879b.egg-info/PKG-INFO
bkp879b.egg-info/SOURCES.txt
bkp879b.egg-info/dependency_links.txt
bkp879b.egg-info/requires.txt
bkp879b.egg-info/top_level.txt