Metadata-Version: 1.1
Name: bkp879b
Version: 1.0.2
Summary: BK Precision 879B/878B Python Library/Driver
Home-page: https://github.com/jimbattin/bkp879b
Author: Jim Battin
Author-email: jrbattin@gmail.com
License: MIT
Download-URL: https://github.com/jimbattin/bkp879b/tarball/1.0.2
Platform: any
